pytextbin/__init__.py
pytextbin/pytextbin.py
PyTextBin-0.0.2.dist-info/LICENSE
PyTextBin-0.0.2.dist-info/METADATA
PyTextBin-0.0.2.dist-info/WHEEL
PyTextBin-0.0.2.dist-info/top_level.txt
PyTextBin-0.0.2.dist-info/RECORD
